0 PUSH_GLOBAL a
1 LOAD_CONST "Functions"
2 STORE_GLOBAL a
3 DEF plus1
4 PUSH_LOCAL y
5 LOAD_FAST y
6 LOAD_CONST 1
7 BINARY_ADD
8 RETURN_VALUE
9 RETURN
10 DEF sub
11 PUSH_LOCAL e
12 PUSH_LOCAL r
13 LOAD_FAST e
14 LOAD_FAST r
15 BINARY_SUBSTRACT
16 RETURN_VALUE
17 RETURN
18 DEF map
19 PUSH_LOCAL n
20 LOAD_FAST n
21 LOAD_GLOBAL len
22 LOAD_CONST 1
23 COMPARE_OP ==
24 JUMP_IF_FALSE 29
25 LOAD_FAST n
26 LOAD_GLOBAL first
27 RETURN_VALUE
28 JUMP_ABSOLUTE 38
29 LOAD_FAST n
30 LOAD_GLOBAL first
31 LOAD_GLOBAL write
32 CALL_FUNCTION 1
33 LOAD_FAST n
34 LOAD_GLOBAL rest
35 LOAD_GLOBAL map
36 CALL_FUNCTION 1
37 RETURN_VALUE
38 RETURN
39 DEF Main
40 LOAD_GLOBAL a
41 STORE_GLOBAL a
42 LOAD_CONST 20
43 LOAD_CONST 420
44 LOAD_GLOBAL sub
45 CALL_FUNCTION 1
46 LOAD_GLOBAL write
47 CALL_FUNCTION 1
48 END
