0 PUSH_GLOBAL programName
1 LOAD_CONST "My Monkey App"
2 STORE_GLOBAL programName
3 DEF fibonacci
4 PUSH_LOCAL x
5 LOAD_FAST x
6 LOAD_CONST 0
7 COMPARE_OP ==
8 JUMP_IF_FALSE 12
9 LOAD_CONST 0
10 RETURN_VALUE
11 JUMP_ABSOLUTE 31
12 LOAD_FAST x
13 LOAD_CONST 1
14 COMPARE_OP ==
15 JUMP_IF_FALSE 19
16 LOAD_CONST 1
17 RETURN_VALUE
18 JUMP_ABSOLUTE 31
19 LOAD_FAST x
20 LOAD_CONST 1
21 BINARY_SUBSTRACT
22 LOAD_GLOBAL fibonacci
23 CALL_FUNCTION 1
24 LOAD_FAST x
25 LOAD_CONST 2
26 BINARY_SUBSTRACT
27 LOAD_GLOBAL fibonacci
28 CALL_FUNCTION 1
29 BINARY_ADD
30 RETURN_VALUE
31 RETURN
32 DEF map
33 PUSH_LOCAL n
34 LOAD_FAST n
35 LOAD_GLOBAL write
36 CALL_FUNCTION 1
37 LOAD_FAST n
38 LOAD_GLOBAL len
39 LOAD_CONST 1
40 COMPARE_OP ==
41 JUMP_IF_FALSE 46
42 LOAD_FAST n
43 LOAD_GLOBAL first
44 RETURN_VALUE
45 JUMP_ABSOLUTE 57
46 LOAD_CONST "=>"
47 LOAD_FAST n
48 LOAD_GLOBAL first
49 BINARY_ADD
50 LOAD_GLOBAL write
51 CALL_FUNCTION 1
52 LOAD_FAST n
53 LOAD_GLOBAL rest
54 LOAD_GLOBAL map
55 CALL_FUNCTION 1
56 RETURN_VALUE
57 RETURN
58 DEF fibonacci_Fast
59 PUSH_LOCAL number
60 LOAD_FAST number
61 LOAD_CONST 2
62 COMPARE_OP <
63 JUMP_IF_FALSE 67
64 LOAD_FAST number
65 RETURN_VALUE
66 JUMP_ABSOLUTE 79
67 LOAD_FAST number
68 LOAD_CONST 1
69 BINARY_SUBSTRACT
70 LOAD_GLOBAL fibonacci_Fast
71 CALL_FUNCTION 1
72 LOAD_FAST number
73 LOAD_CONST 2
74 BINARY_SUBSTRACT
75 LOAD_GLOBAL fibonacci_Fast
76 CALL_FUNCTION 1
77 BINARY_ADD
78 RETURN_VALUE
79 RETURN
80 DEF sum
81 PUSH_LOCAL a
82 PUSH_LOCAL b
83 PUSH_LOCAL c
84 LOAD_FAST a
85 LOAD_FAST b
86 LOAD_FAST c
87 LOAD_FAST c
88 LOAD_GLOBAL fibonacci_Fast
89 CALL_FUNCTION 1
90 BINARY_ADD
91 BINARY_ADD
92 BINARY_ADD
93 RETURN_VALUE
94 RETURN
95 DEF Main
96 LOAD_GLOBAL programName
97 STORE_GLOBAL programName
98 LOAD_CONST 2
99 LOAD_CONST 2
100 LOAD_CONST 9
101 LOAD_GLOBAL sum
102 CALL_FUNCTION 3
103 LOAD_GLOBAL write
104 CALL_FUNCTION 1
105 END
