0 PUSH_GLOBAL_I p
1 DEF test
2 PUSH_LOCAL_I y
3 PUSH_LOCAL_I x
4 PUSH_LOCAL_I r
5 LOAD_CONST 1
6 STORE_FAST r
7 LOAD_CONST 7
8 STORE_FAST x
9 LOAD_FAST x
10 LOAD_CONST 8
11 COMPARE_OP !=
12 JUMP_IF_FALSE 16
13 LOAD_FAST x
14 LOAD_GLOBAL write
15 CALL_FUNCTION 1
17 LOAD_CONST 8
18 LOAD_CONST 7
19 COMPARE_OP ==
20 JUMP_IF_FALSE 25
21 LOAD_CONST 7
22 LOAD_GLOBAL write
23 CALL_FUNCTION 1
24 JUMP_ABSOLUTE 52
25 LOAD_CONST 8
26 LOAD_CONST 3
27 COMPARE_OP ==
28 JUMP_IF_FALSE 33
29 LOAD_CONST 3
30 LOAD_GLOBAL write
31 CALL_FUNCTION 1
32 JUMP_ABSOLUTE 52
33 LOAD_CONST 8
34 LOAD_CONST 4
35 COMPARE_OP ==
36 JUMP_IF_FALSE 41
37 LOAD_CONST 4
38 LOAD_GLOBAL write
39 CALL_FUNCTION 1
40 JUMP_ABSOLUTE 52
41 LOAD_CONST 8
42 LOAD_CONST 8
43 COMPARE_OP ==
44 JUMP_IF_FALSE 49
45 LOAD_CONST 8
46 LOAD_GLOBAL write
47 CALL_FUNCTION 1
48 JUMP_ABSOLUTE 52
49 LOAD_CONST 10
50 LOAD_GLOBAL write
51 CALL_FUNCTION 1
52 LOAD_CONST 4
53 RETURN_VALUE 
54 DEF Main
55 LOAD_CONST 6
56 LOAD_GLOBAL test
57 CALL_FUNCTION 1
58 STORE_GLOBAL p
59 LOAD_CONST 3
60 STORE_GLOBAL p
61 END